pycryptomod/__init__.py
pycryptomod/module.py
pycryptomod-0.1.0.dist-info/LICENSE.txt
pycryptomod-0.1.0.dist-info/METADATA
pycryptomod-0.1.0.dist-info/WHEEL
pycryptomod-0.1.0.dist-info/top_level.txt
pycryptomod-0.1.0.dist-info/RECORD
