Metadata-Version: 2.1
Name: pycryptomod
Version: 0.1.0
Summary: A simpler plug and play module for prototyping cryptography techniques
Author: Aditya Bharadwaj
Author-email: adityabharadwaj47@gmail.com
License: MIT
License-File: LICENSE.txt
Requires-Dist: pycryptodome
